llmlingua/__init__.py
llmlingua/prompt_compressor.py
llmlingua/utils.py
llmlingua/version.py
llmlingua-0.2.1.dist-info/LICENSE
llmlingua-0.2.1.dist-info/METADATA
llmlingua-0.2.1.dist-info/WHEEL
llmlingua-0.2.1.dist-info/top_level.txt
llmlingua-0.2.1.dist-info/RECORD
