Metadata-Version: 2.1
Name: llmlingua
Version: 0.2.1
Summary: To speed up LLMs' inference and enhance LLM's perceive of key information, compress the prompt and KV-Cache, which achieves up to 20x compression with minimal performance loss.
Home-page: https://github.com/microsoft/LLMLingua
Author: The LLMLingua team
Author-email: hjiang@microsoft.com
License: MIT License
Keywords: Prompt Compression,LLMs,Inference Acceleration,Black-box LLMs,Efficient LLMs
Classifier: Intended Audience :: Science/Research
Classifier: Development Status :: 3 - Alpha
Classifier: Programming Language :: Python :: 3
Classifier: Topic :: Scientific/Engineering :: Artificial Intelligence
Requires-Python: >=3.8.0
License-File: LICENSE
Requires-Dist: transformers >=4.26.0
Requires-Dist: accelerate
Requires-Dist: torch
Requires-Dist: tiktoken
Requires-Dist: nltk
Requires-Dist: numpy
Provides-Extra: dev
Requires-Dist: transformers >=4.26.0 ; extra == 'dev'
Requires-Dist: accelerate ; extra == 'dev'
Requires-Dist: torch ; extra == 'dev'
Requires-Dist: tiktoken ; extra == 'dev'
Requires-Dist: nltk ; extra == 'dev'
Requires-Dist: numpy ; extra == 'dev'
Requires-Dist: black ==21.4b0 ; extra == 'dev'
Requires-Dist: flake8 >=3.8.3 ; extra == 'dev'
Requires-Dist: isort >=5.5.4 ; extra == 'dev'
Requires-Dist: pre-commit ; extra == 'dev'
Requires-Dist: pytest ; extra == 'dev'
Requires-Dist: pytest-xdist ; extra == 'dev'
Provides-Extra: quality
Requires-Dist: black ==21.4b0 ; extra == 'quality'
Requires-Dist: flake8 >=3.8.3 ; extra == 'quality'
Requires-Dist: isort >=5.5.4 ; extra == 'quality'
Requires-Dist: pre-commit ; extra == 'quality'
Requires-Dist: pytest ; extra == 'quality'
Requires-Dist: pytest-xdist ; extra == 'quality'
